mcp_generate_mind/__init__.py
mcp_generate_mind/__main__.py
mcp_generate_mind/server.py
mcp_generate_mind/server_mcp.py
mcp_generate_mind/start_server.py
mcp_generate_mind/markdown/1759115178_cfc1392d.html
mcp_generate_mind/markdown/1759115178_cfc1392d.md
mcp_generate_mind/models/__init__.py
mcp_generate_mind/models/mind.py
mcp_generate_mind/utils/__init__.py
mcp_generate_mind/utils/config.py
mcp_generate_mind/utils/custom_logger.py
mcp_generate_mind-0.6.0.dist-info/METADATA
mcp_generate_mind-0.6.0.dist-info/WHEEL
mcp_generate_mind-0.6.0.dist-info/entry_points.txt
mcp_generate_mind-0.6.0.dist-info/RECORD
