Metadata-Version: 2.4
Name: mcp-generate-mind
Version: 0.6.0
Summary: MCP服务器用于思维导图的生成
Author-email: chenzeng <chenzeng@cmss.chinamobile.com>
Requires-Python: >=3.11
Requires-Dist: aiohttp>=3.9.0
Requires-Dist: fastapi>=0.104.0
Requires-Dist: gunicorn>=23.0.0
Requires-Dist: httpx>=0.25.0
Requires-Dist: mcp>=1.9.0
Requires-Dist: pydantic-settings>=2.0.0
Requires-Dist: pydantic>=2.4.0
Requires-Dist: python-dotenv>=1.0.0
Requires-Dist: requests>=2.31.0
Requires-Dist: uvicorn[standard]>=0.24.0
Provides-Extra: dev
Requires-Dist: black>=23.9.0; extra == 'dev'
Requires-Dist: gunicorn>=23.0.0; extra == 'dev'
Requires-Dist: isort>=5.12.0; extra == 'dev'
Requires-Dist: mypy>=1.6.0; extra == 'dev'
Requires-Dist: pre-commit>=3.5.0; extra == 'dev'
Requires-Dist: pytest-asyncio>=0.21.0; extra == 'dev'
Requires-Dist: pytest-httpx>=0.26.0; extra == 'dev'
Requires-Dist: pytest>=7.4.0; extra == 'dev'
